ultrasound_metrics/__about__.py
ultrasound_metrics/__init__.py
ultrasound_metrics/_utils/__init__.py
ultrasound_metrics/_utils/array_api.py
ultrasound_metrics/channel/__init__.py
ultrasound_metrics/channel/noise.py
ultrasound_metrics/data/__init__.py
ultrasound_metrics/data/downloads.py
ultrasound_metrics/data/uff.py
ultrasound_metrics/data/visualize_bmode.py
ultrasound_metrics/interactive/__init__.py
ultrasound_metrics/interactive/napari_utils.py
ultrasound_metrics/metrics/__init__.py
ultrasound_metrics/metrics/clip.py
ultrasound_metrics/metrics/cnr.py
ultrasound_metrics/metrics/coherence.py
ultrasound_metrics/metrics/contrast.py
ultrasound_metrics/metrics/fwhm.py
ultrasound_metrics/metrics/gcnr.py
ultrasound_metrics/metrics/rf_snr.py
ultrasound_metrics/metrics/sharpness.py
ultrasound_metrics/metrics/sll.py
ultrasound_metrics/metrics/tsnr.py
ultrasound_metrics/metrics/utils.py
ultrasound_metrics/motion/__init__.py
ultrasound_metrics/motion/corrcoef.py
ultrasound_metrics/roi/__init__.py
ultrasound_metrics/roi/masks.py
ultrasound_metrics/utils/__init__.py
ultrasound_metrics/utils/analysis_utils.py
ultrasound_metrics/utils/phantom_utils.py
ultrasound_metrics/utils/utils.py
ultrasound_metrics-0.1.0.dist-info/METADATA
ultrasound_metrics-0.1.0.dist-info/WHEEL
ultrasound_metrics-0.1.0.dist-info/RECORD
