Metadata-Version: 2.4
Name: ultrasound-metrics
Version: 0.1.0
Summary: Metrics for ultrasound data and images
Project-URL: Homepage, https://forest-neurotech-ultrasound-metrics.readthedocs-hosted.com/en/latest/
Project-URL: Repository, https://github.com/Forest-Neurotech/ultrasound-metrics
Project-URL: Documentation, https://Forest-Neurotech.github.io/ultrasound-metrics/
Author-email: Charles Guan <charles@forestneurotech.org>, Ansh Kharbanda <ansh@forestneurotech.org>, Jake McCall <jake@forestneurotech.org>, Alex Rockhill <alex@forestneurotech.org>
Maintainer-email: Forest Neurotech Developers <software-update@forestneurotech.org>
Keywords: python
Classifier: Intended Audience :: Developers
Classifier: Programming Language :: Python
Classifier: Programming Language :: Python :: 3
Classifier: Programming Language :: Python :: 3.10
Classifier: Programming Language :: Python :: 3.11
Classifier: Programming Language :: Python :: 3.12
Classifier: Programming Language :: Python :: 3.13
Classifier: Topic :: Software Development :: Libraries :: Python Modules
Requires-Python: <4.0,>=3.10
Requires-Dist: array-api-compat>=1.11.0
Requires-Dist: array-api-extra>=0.7.0
Requires-Dist: beartype>=0.16.0
Requires-Dist: einops>=0.8.0
Requires-Dist: equinox>=0.11.11
Requires-Dist: jax>=0.4.38
Requires-Dist: jaxtyping>=0.3.0
Requires-Dist: matplotlib>=3.9.4
Requires-Dist: numpy>=2.0.1
Requires-Dist: opencv-python>=4.11.0
Requires-Dist: pandas>=2.2.2
Requires-Dist: pyyaml>=5.4.1
Requires-Dist: requests>=2.25.0
Requires-Dist: scikit-image>=0.25.0
Requires-Dist: scikit-posthocs>=0.11.3
Requires-Dist: scipy>=1.9.0
Requires-Dist: statsmodels>=0.14.4
Requires-Dist: xarray>=2024.10.0
Provides-Extra: backends
Requires-Dist: jax>=0.4.32; (python_version >= '3.10') and extra == 'backends'
Requires-Dist: numpy>=1.22; extra == 'backends'
Requires-Dist: torch>=1.13; extra == 'backends'
Provides-Extra: datasets
Requires-Dist: pyuff-ustb>=3.0.0; extra == 'datasets'
Provides-Extra: interactive
Requires-Dist: napari[all]>=0.5.0; extra == 'interactive'
Provides-Extra: progress
Requires-Dist: tqdm>=4.0.0; extra == 'progress'
